cloudguard_modules/__init__.py
cloudguard_modules/gcp/modules/compute/gcs.py
cloudguard_modules/gcp/modules/compute/metadata.py
cloudguard_modules/gcp/modules/compute/vm.py
cloudguard_modules/gcp/modules/iam/iam_admin.py
cloudguard_modules/gcp/modules/network/cdn.py
cloudguard_modules/gcp/modules/network/dns.py
cloudguard_modules/gcp/modules/network/firewall.py
cloudguard_modules/gcp/modules/network/load_balancing.py
cloudguard_modules/gcp/modules/network/vpc.py
cloudguard_modules/gcp/modules/security/secret_manager.py
cloudguard_modules/gcp/scripts/export_iam_bindings.sh
cloudguard_modules/gcp/utils/file.py
cloudguard_modules/gcp/utils/json.py
cloudguard_modules/gcp/utils/shell.py
cloudguard_modules-1.0.3.dist-info/LICENSE
cloudguard_modules-1.0.3.dist-info/METADATA
cloudguard_modules-1.0.3.dist-info/WHEEL
cloudguard_modules-1.0.3.dist-info/RECORD
